basecfg/__init__.py
basecfg/basecfg.py
basecfg/py.typed
basecfg-2.1.1.dist-info/LICENSE
basecfg-2.1.1.dist-info/METADATA
basecfg-2.1.1.dist-info/WHEEL
basecfg-2.1.1.dist-info/top_level.txt
basecfg-2.1.1.dist-info/RECORD
