Metadata-Version: 2.1
Name: basecfg
Version: 2.1.1
Summary: typed 12-factor app configuration helper
Author-email: Ben Burke <actualben@users.noreply.github.com>, edenceHealth NV <info@edence.health>
Project-URL: Homepage, https://github.com/edencehealth/basecfg
Project-URL: Bug Tracker, https://github.com/edencehealth/basecfg/issues
Classifier: Programming Language :: Python :: 3
Classifier: License :: OSI Approved :: GNU Lesser General Public License v2 (LGPLv2)
Classifier: Operating System :: OS Independent
Requires-Python: >=3.10
License-File: LICENSE
